MANIFEST.in
README.md
setup.cfg
setup.py
tuneRs/__init__.py
tuneRs/space.py
tuneRs/tuneRs.py
tuneRs.egg-info/PKG-INFO
tuneRs.egg-info/SOURCES.txt
tuneRs.egg-info/dependency_links.txt
tuneRs.egg-info/requires.txt
tuneRs.egg-info/top_level.txt