Metadata-Version: 2.1
Name: tuneRs
Version: 0.56
Summary: Package for tuning hyperparameters with resampling methods
Home-page: https://github.com/metriczulu/tuneRs
Author: Shane Stephenson / metriczulu
Author-email: stephenson.shane.a@gmail.com
License: None
Download-URL: https://github.com/metriczulu/tuneRs/archive/v0.56.tar.gz
Platform: UNKNOWN
